ustat_var/__init__.py
ustat_var/_version.py
ustat_var/generate_test_data.py
ustat_var/lamb_sum.py
ustat_var/makec.py
ustat_var/sampc.py
ustat_var/ustat_samp_covar.py
ustat_var/varcovar.py
ustat_var-0.3.4.dist-info/METADATA
ustat_var-0.3.4.dist-info/WHEEL
ustat_var-0.3.4.dist-info/licenses/LICENSE
ustat_var-0.3.4.dist-info/RECORD
