Metadata-Version: 2.4
Name: ustat_var
Version: 0.3.4
Summary: Computing unbiased variance estimators
Project-URL: Documentation, https://ustat-var.readthedocs.io/en/latest/
Project-URL: Repository, https://github.com/jkmulq/ustat_var
Project-URL: Bug Tracker, https://github.com/jkmulq/ustat_var/issues
Author-email: "Evan K. Rose" <ekrose@uchicago.edu>, Yotam Shem-Tov <shemtov@econ.ucla.edu>, "Jonathan T. Schellenberg" <jschellenberg@econ.berkeley.edu>, Jack Mulqueeney <jmulqueeney@uchicag.edu>
Maintainer-email: Jack Mulqueeney <jmulqueeney@uchicago.edu>
License-Expression: MIT
License-File: LICENSE
Classifier: Operating System :: OS Independent
Classifier: Programming Language :: Python :: 3
Requires-Python: >=3.9
